health_core/__init__.py
health_core/exceptions/__init__.py
health_core/exceptions/health_exception.py
health_core/helper/__init__.py
health_core/helper/data_helper.py
health_core/helper/date_time_helper.py
health_core/validators/__init__.py
health_core/validators/claim_validator.py
health_core/validators/dependents_validator.py
health_core/validators/health_policy_validator.py
tests/__init__.py
tests/test_validate.py
x22249184_healthinsurance-1.0.0.dist-info/LICENSE.txt
x22249184_healthinsurance-1.0.0.dist-info/METADATA
x22249184_healthinsurance-1.0.0.dist-info/WHEEL
x22249184_healthinsurance-1.0.0.dist-info/top_level.txt
x22249184_healthinsurance-1.0.0.dist-info/RECORD
