Metadata-Version: 2.1
Name: x22249184-healthinsurance
Version: 1.0.0
Summary: Health Insurance Library
Home-page: https://github.com/GADDE-AKHILA/x22249184_healthinsurance_library
Author: GADDE-AKHILA
Author-email: akhilagadde2023@gmail.com
License: UNKNOWN
Platform: UNKNOWN
Classifier: Programming Language :: Python :: 3
Classifier: License :: OSI Approved :: MIT License
Classifier: Operating System :: OS Independent
Requires-Python: >=3.6
License-File: LICENSE.txt
